dsframeworklib/__init__.py
dsframeworklib/ds_client.py
dsframeworklib/ds_process.py
dsframeworklib/utils/__init__.py
dsframeworklib/utils/logger.py
dsframeworklib/utils/message.py
dsframeworklib/utils/socketUtil.py
dsframeworklib-0.0.14.dist-info/LICENSE
dsframeworklib-0.0.14.dist-info/METADATA
dsframeworklib-0.0.14.dist-info/WHEEL
dsframeworklib-0.0.14.dist-info/top_level.txt
dsframeworklib-0.0.14.dist-info/RECORD
