Metadata-Version: 2.1
Name: dsframeworklib
Version: 0.0.14
Summary: Basic distributed system framework, to simulate working of distributed systems
Author: appmonster007
License: MIT
Platform: UNKNOWN
License-File: LICENSE
